gcp_provider/__init__.py
gcp_provider/py.typed
gcp_provider/resources/__init__.py
gcp_provider/resources/gke.py
gcp_provider/resources/secret.py
pragmatiks_gcp_provider-0.66.0.dist-info/WHEEL
pragmatiks_gcp_provider-0.66.0.dist-info/METADATA
pragmatiks_gcp_provider-0.66.0.dist-info/RECORD
