Metadata-Version: 2.3
Name: pragmatiks-gcp-provider
Version: 0.66.0
Summary: GCP provider for Pragmatiks
Author: Pragmatiks
Author-email: Pragmatiks <team@pragmatiks.io>
Requires-Dist: pragmatiks-sdk>=0.6.0
Requires-Dist: google-cloud-container>=2.50.0
Requires-Dist: google-cloud-logging>=3.10.0
Requires-Dist: google-cloud-secret-manager>=2.20.0
Requires-Python: >=3.13
